nonebot_plugin_nodice/__init__.py
nonebot_plugin_nodice/calculator.py
nonebot_plugin_nodice/character.py
nonebot_plugin_nodice/constant.py
nonebot_plugin_nodice/data.py
nonebot_plugin_nodice/deck.py
nonebot_plugin_nodice/exception.py
nonebot_plugin_nodice/handle.py
nonebot_plugin_nodice/help.py
nonebot_plugin_nodice/message.py
nonebot_plugin_nodice/nb.py
nonebot_plugin_nodice/nb2.py
nonebot_plugin_nodice/others.py
nonebot_plugin_nodice/pyproject.toml
nonebot_plugin_nodice/README.md
nonebot_plugin_nodice/test.py
nonebot_plugin_nodice/utils.py
nonebot_plugin_nodice-2.0.0a1.dist-info/WHEEL
nonebot_plugin_nodice-2.0.0a1.dist-info/METADATA
nonebot_plugin_nodice-2.0.0a1.dist-info/RECORD
